[
  {
    "id": "1a10b27a-4ce2-4425-9ad7-2a9f0dddc7ae",
    "data": [
      {
        "text": "I\u0027m bored",
        "userDefined": false
      }
    ],
    "isTemplate": false,
    "count": 0,
    "updated": 1539785892
  },
  {
    "id": "c610e42f-6b68-42f0-89ba-5a4cf12aa066",
    "data": [
      {
        "text": "I want to do activity",
        "userDefined": false
      }
    ],
    "isTemplate": false,
    "count": 0,
    "updated": 1539785892
  },
  {
    "id": "93a81d13-87c5-4eca-bb59-e577213bec6a",
    "data": [
      {
        "text": "I want to do activities",
        "userDefined": false
      }
    ],
    "isTemplate": false,
    "count": 0,
    "updated": 1539785892
  },
  {
    "id": "48a1aa6c-86e6-41cb-a41a-6fc045e8f747",
    "data": [
      {
        "text": "any activities around",
        "userDefined": false
      }
    ],
    "isTemplate": false,
    "count": 0,
    "updated": 1539785892
  },
  {
    "id": "f8e269cf-92d5-450b-8a8d-3ead27ad84c1",
    "data": [
      {
        "text": "I\u0027m bored, suggest me some activities",
        "userDefined": false
      }
    ],
    "isTemplate": false,
    "count": 0,
    "updated": 1539785892
  },
  {
    "id": "31078982-45a0-43c3-9683-88ec6ac522b1",
    "data": [
      {
        "text": "I\u0027m bored, suggest me an activity",
        "userDefined": false
      }
    ],
    "isTemplate": false,
    "count": 0,
    "updated": 1539785892
  },
  {
    "id": "9a3a55a1-597f-4dbc-9ddf-37ffe1e0499b",
    "data": [
      {
        "text": "find activity around  me",
        "userDefined": false
      }
    ],
    "isTemplate": false,
    "count": 0,
    "updated": 1539785892
  },
  {
    "id": "bfbbc648-14e1-4f3b-9e9c-ede3d0b79f6a",
    "data": [
      {
        "text": "find activity near me",
        "userDefined": false
      }
    ],
    "isTemplate": false,
    "count": 0,
    "updated": 1539785892
  },
  {
    "id": "4293e8bf-423d-4c08-acb2-1e6072a549f6",
    "data": [
      {
        "text": "I want to do activity in ",
        "userDefined": false
      },
      {
        "text": "Nice",
        "alias": "city",
        "meta": "@city",
        "userDefined": false
      },
      {
        "text": " at ",
        "userDefined": false
      },
      {
        "text": "8 pm",
        "alias": "datetime",
        "meta": "@sys.date-time",
        "userDefined": false
      }
    ],
    "isTemplate": false,
    "count": 0,
    "updated": 1539785892
  },
  {
    "id": "b123c666-c15f-4a4e-ac36-a484826111f6",
    "data": [
      {
        "text": "I want to do activity in ",
        "userDefined": false
      },
      {
        "text": "December",
        "alias": "datetime",
        "meta": "@sys.date-time",
        "userDefined": false
      },
      {
        "text": " in ",
        "userDefined": false
      },
      {
        "text": "Nice",
        "alias": "city",
        "meta": "@city",
        "userDefined": false
      }
    ],
    "isTemplate": false,
    "count": 0,
    "updated": 1539785892
  },
  {
    "id": "3ec4625e-4ee8-48f4-81a2-26a1c7b209f3",
    "data": [
      {
        "text": "I want to do activity in ",
        "userDefined": false
      },
      {
        "text": "today",
        "alias": "datetime",
        "meta": "@sys.date-time",
        "userDefined": false
      },
      {
        "text": " in  ",
        "userDefined": false
      },
      {
        "text": "Nice",
        "alias": "city",
        "meta": "@city",
        "userDefined": false
      }
    ],
    "isTemplate": false,
    "count": 0,
    "updated": 1539785892
  },
  {
    "id": "403d99b1-bbaf-403d-9465-77ffa9f3b038",
    "data": [
      {
        "text": "I want to do activity in ",
        "userDefined": false
      },
      {
        "text": "Nice",
        "alias": "city",
        "meta": "@city",
        "userDefined": false
      },
      {
        "text": " on ",
        "userDefined": false
      },
      {
        "text": "14th August",
        "alias": "datetime",
        "meta": "@sys.date-time",
        "userDefined": false
      }
    ],
    "isTemplate": false,
    "count": 0,
    "updated": 1539785892
  },
  {
    "id": "8441ae32-0b51-4d5f-9b33-0b883554854c",
    "data": [
      {
        "text": "Show me something to do ",
        "userDefined": false
      },
      {
        "text": "Nice",
        "alias": "city",
        "meta": "@city",
        "userDefined": false
      },
      {
        "text": " at ",
        "userDefined": false
      },
      {
        "text": "8 pm",
        "alias": "datetime",
        "meta": "@sys.date-time",
        "userDefined": false
      }
    ],
    "isTemplate": false,
    "count": 0,
    "updated": 1539785892
  },
  {
    "id": "58037e6c-62b7-44bb-bce1-dc07bca3538a",
    "data": [
      {
        "text": "Show me something to do  ",
        "userDefined": false
      },
      {
        "text": "December",
        "alias": "datetime",
        "meta": "@sys.date-time",
        "userDefined": false
      },
      {
        "text": " in ",
        "userDefined": false
      },
      {
        "text": "Nice",
        "alias": "city",
        "meta": "@city",
        "userDefined": false
      }
    ],
    "isTemplate": false,
    "count": 0,
    "updated": 1539785892
  },
  {
    "id": "03387bb8-eb0a-48b8-8c26-38dcbb55f6cb",
    "data": [
      {
        "text": "Show me something to do ",
        "userDefined": false
      },
      {
        "text": "today",
        "alias": "datetime",
        "meta": "@sys.date-time",
        "userDefined": false
      },
      {
        "text": " in  ",
        "userDefined": false
      },
      {
        "text": "Nice",
        "alias": "city",
        "meta": "@city",
        "userDefined": false
      }
    ],
    "isTemplate": false,
    "count": 0,
    "updated": 1539785892
  },
  {
    "id": "51ad4466-7382-4935-bbc8-ca5abd3404d8",
    "data": [
      {
        "text": "Show me something to do  ",
        "userDefined": false
      },
      {
        "text": "Nice",
        "alias": "city",
        "meta": "@city",
        "userDefined": false
      },
      {
        "text": " on ",
        "userDefined": false
      },
      {
        "text": "14th August",
        "alias": "datetime",
        "meta": "@sys.date-time",
        "userDefined": false
      }
    ],
    "isTemplate": false,
    "count": 0,
    "updated": 1539785892
  },
  {
    "id": "974855f9-2fc6-4dff-b12b-95d026e8682e",
    "data": [
      {
        "text": "Any activities in ",
        "userDefined": false
      },
      {
        "text": "Nice",
        "alias": "city",
        "meta": "@city",
        "userDefined": false
      },
      {
        "text": " at ",
        "userDefined": false
      },
      {
        "text": "8 pm",
        "alias": "datetime",
        "meta": "@sys.date-time",
        "userDefined": false
      }
    ],
    "isTemplate": false,
    "count": 0,
    "updated": 1539785892
  },
  {
    "id": "f46c658e-7c2a-4857-84d1-5dafd83f9934",
    "data": [
      {
        "text": "Any activities in  ",
        "userDefined": false
      },
      {
        "text": "December",
        "alias": "datetime",
        "meta": "@sys.date-time",
        "userDefined": false
      },
      {
        "text": " in ",
        "userDefined": false
      },
      {
        "text": "Nice",
        "alias": "city",
        "meta": "@city",
        "userDefined": false
      }
    ],
    "isTemplate": false,
    "count": 0,
    "updated": 1539785892
  },
  {
    "id": "a752583a-d40b-4791-ae68-463f8c59380b",
    "data": [
      {
        "text": "Any activities in  ",
        "userDefined": false
      },
      {
        "text": "today",
        "alias": "datetime",
        "meta": "@sys.date-time",
        "userDefined": false
      },
      {
        "text": " in  ",
        "userDefined": false
      },
      {
        "text": "Nice",
        "alias": "city",
        "meta": "@city",
        "userDefined": false
      }
    ],
    "isTemplate": false,
    "count": 0,
    "updated": 1539785892
  },
  {
    "id": "f8fa6547-dc07-4125-99bc-45387f405291",
    "data": [
      {
        "text": "Any activities in  ",
        "userDefined": false
      },
      {
        "text": "Nice",
        "alias": "city",
        "meta": "@city",
        "userDefined": false
      },
      {
        "text": " on ",
        "userDefined": false
      },
      {
        "text": "14th August",
        "alias": "datetime",
        "meta": "@sys.date-time",
        "userDefined": false
      }
    ],
    "isTemplate": false,
    "count": 0,
    "updated": 1539785892
  },
  {
    "id": "910e5672-71df-4e48-a167-78b67c234760",
    "data": [
      {
        "text": "I\u0027m bored, suggest me some activities in ",
        "userDefined": false
      },
      {
        "text": "Nice",
        "alias": "city",
        "meta": "@city",
        "userDefined": false
      },
      {
        "text": " at ",
        "userDefined": false
      },
      {
        "text": "8 pm",
        "alias": "datetime",
        "meta": "@sys.date-time",
        "userDefined": false
      }
    ],
    "isTemplate": false,
    "count": 0,
    "updated": 1539785892
  },
  {
    "id": "c49ffe0f-2a8f-4503-8bee-98e27b1a939f",
    "data": [
      {
        "text": "I\u0027m bored, suggest me some activities in ",
        "userDefined": false
      },
      {
        "text": "December",
        "alias": "datetime",
        "meta": "@sys.date-time",
        "userDefined": false
      },
      {
        "text": " in ",
        "userDefined": false
      },
      {
        "text": "Nice",
        "alias": "city",
        "meta": "@city",
        "userDefined": false
      }
    ],
    "isTemplate": false,
    "count": 0,
    "updated": 1539785892
  },
  {
    "id": "0c11be05-7e58-4dea-9604-654653f55146",
    "data": [
      {
        "text": "I\u0027m bored, suggest me some activities on ",
        "userDefined": false
      },
      {
        "text": "today",
        "alias": "datetime",
        "meta": "@sys.date-time",
        "userDefined": false
      },
      {
        "text": " in  ",
        "userDefined": false
      },
      {
        "text": "Nice",
        "alias": "city",
        "meta": "@city",
        "userDefined": false
      }
    ],
    "isTemplate": false,
    "count": 0,
    "updated": 1539785892
  },
  {
    "id": "8cef19ea-1427-4807-9b87-bf90683be1aa",
    "data": [
      {
        "text": "I\u0027m bored, suggest me some activities in ",
        "userDefined": false
      },
      {
        "text": "Nice",
        "alias": "city",
        "meta": "@city",
        "userDefined": false
      },
      {
        "text": " on ",
        "userDefined": false
      },
      {
        "text": "14th August",
        "alias": "datetime",
        "meta": "@sys.date-time",
        "userDefined": false
      }
    ],
    "isTemplate": false,
    "count": 0,
    "updated": 1539785892
  },
  {
    "id": "eacfca55-20e1-40c5-8a53-02e5e8836350",
    "data": [
      {
        "text": "Find me an activity ",
        "userDefined": false
      },
      {
        "text": "Nice",
        "alias": "city",
        "meta": "@city",
        "userDefined": false
      },
      {
        "text": " at ",
        "userDefined": false
      },
      {
        "text": "8 pm",
        "alias": "datetime",
        "meta": "@sys.date-time",
        "userDefined": false
      }
    ],
    "isTemplate": false,
    "count": 0,
    "updated": 1539785892
  },
  {
    "id": "30217af0-7b8a-4f3a-9aa4-7d68aa2ed58a",
    "data": [
      {
        "text": "Find me an activity ",
        "userDefined": false
      },
      {
        "text": "December",
        "alias": "datetime",
        "meta": "@sys.date-time",
        "userDefined": false
      },
      {
        "text": " in ",
        "userDefined": false
      },
      {
        "text": "Nice",
        "alias": "city",
        "meta": "@city",
        "userDefined": false
      }
    ],
    "isTemplate": false,
    "count": 0,
    "updated": 1539785892
  },
  {
    "id": "9f285351-4b31-404b-98ff-439c02cb433d",
    "data": [
      {
        "text": "Find me an activity ",
        "userDefined": false
      },
      {
        "text": "today",
        "alias": "datetime",
        "meta": "@sys.date-time",
        "userDefined": false
      },
      {
        "text": " in  ",
        "userDefined": false
      },
      {
        "text": "Nice",
        "alias": "city",
        "meta": "@city",
        "userDefined": false
      }
    ],
    "isTemplate": false,
    "count": 0,
    "updated": 1539785892
  },
  {
    "id": "3e9b3451-bf57-4352-bbf5-b5c2d121bcab",
    "data": [
      {
        "text": "Find me an activity ",
        "userDefined": false
      },
      {
        "text": "Nice",
        "alias": "city",
        "meta": "@city",
        "userDefined": false
      },
      {
        "text": " on ",
        "userDefined": false
      },
      {
        "text": "14th August",
        "alias": "datetime",
        "meta": "@sys.date-time",
        "userDefined": false
      }
    ],
    "isTemplate": false,
    "count": 0,
    "updated": 1539785892
  },
  {
    "id": "32ae7e7d-021b-467c-ac41-c3e8edc9d90a",
    "data": [
      {
        "text": "Activity in  ",
        "userDefined": false
      },
      {
        "text": "Nice",
        "alias": "city",
        "meta": "@city",
        "userDefined": false
      },
      {
        "text": " at ",
        "userDefined": false
      },
      {
        "text": "8 pm",
        "alias": "datetime",
        "meta": "@sys.date-time",
        "userDefined": false
      }
    ],
    "isTemplate": false,
    "count": 0,
    "updated": 1539785892
  },
  {
    "id": "dbeab0c7-0c3a-486d-9cbf-67b481a179b7",
    "data": [
      {
        "text": "Activity in  ",
        "userDefined": false
      },
      {
        "text": "December",
        "alias": "datetime",
        "meta": "@sys.date-time",
        "userDefined": false
      },
      {
        "text": " in ",
        "userDefined": false
      },
      {
        "text": "Nice",
        "alias": "city",
        "meta": "@city",
        "userDefined": false
      }
    ],
    "isTemplate": false,
    "count": 0,
    "updated": 1539785892
  },
  {
    "id": "94fb4e68-762d-4ebe-85bc-9d8383b99f53",
    "data": [
      {
        "text": "Activity in  ",
        "userDefined": false
      },
      {
        "text": "today",
        "alias": "datetime",
        "meta": "@sys.date-time",
        "userDefined": false
      },
      {
        "text": " in  ",
        "userDefined": false
      },
      {
        "text": "Nice",
        "alias": "city",
        "meta": "@city",
        "userDefined": false
      }
    ],
    "isTemplate": false,
    "count": 0,
    "updated": 1539785892
  },
  {
    "id": "f75297d1-5881-4f1a-86e5-be4fc22100ca",
    "data": [
      {
        "text": "Activity in  ",
        "userDefined": false
      },
      {
        "text": "Nice",
        "alias": "city",
        "meta": "@city",
        "userDefined": false
      },
      {
        "text": " on ",
        "userDefined": false
      },
      {
        "text": "14th August",
        "alias": "datetime",
        "meta": "@sys.date-time",
        "userDefined": false
      }
    ],
    "isTemplate": false,
    "count": 0,
    "updated": 1539785892
  },
  {
    "id": "bd283e47-485e-4aa0-b815-6a4589e408c0",
    "data": [
      {
        "text": "check for some activities in ",
        "userDefined": false
      },
      {
        "text": "Nice",
        "alias": "city",
        "meta": "@city",
        "userDefined": false
      },
      {
        "text": " at ",
        "userDefined": false
      },
      {
        "text": "8 pm",
        "alias": "datetime",
        "meta": "@sys.date-time",
        "userDefined": false
      }
    ],
    "isTemplate": false,
    "count": 0,
    "updated": 1539785892
  },
  {
    "id": "ea53b889-8aae-437e-94e4-8b43608a730d",
    "data": [
      {
        "text": "check for some activities in ",
        "userDefined": false
      },
      {
        "text": "December",
        "alias": "datetime",
        "meta": "@sys.date-time",
        "userDefined": false
      },
      {
        "text": " in ",
        "userDefined": false
      },
      {
        "text": "Nice",
        "alias": "city",
        "meta": "@city",
        "userDefined": false
      }
    ],
    "isTemplate": false,
    "count": 0,
    "updated": 1539785892
  },
  {
    "id": "44ec6089-9c0e-41a7-8c62-945ff6f432d9",
    "data": [
      {
        "text": "check for some activities ",
        "userDefined": false
      },
      {
        "text": "today",
        "alias": "datetime",
        "meta": "@sys.date-time",
        "userDefined": false
      },
      {
        "text": " in  ",
        "userDefined": false
      },
      {
        "text": "Nice",
        "alias": "city",
        "meta": "@city",
        "userDefined": false
      }
    ],
    "isTemplate": false,
    "count": 0,
    "updated": 1539785892
  },
  {
    "id": "e1619c72-050e-4968-9f7d-e5035cabfd85",
    "data": [
      {
        "text": "check for some activities in ",
        "userDefined": false
      },
      {
        "text": "Nice",
        "alias": "city",
        "meta": "@city",
        "userDefined": false
      },
      {
        "text": " on ",
        "userDefined": false
      },
      {
        "text": "14th August",
        "alias": "datetime",
        "meta": "@sys.date-time",
        "userDefined": false
      }
    ],
    "isTemplate": false,
    "count": 0,
    "updated": 1539785892
  },
  {
    "id": "5108e9b9-275d-4058-9f81-218c0621b815",
    "data": [
      {
        "text": "Suggest me some activities in ",
        "userDefined": false
      },
      {
        "text": "Nice",
        "alias": "city",
        "meta": "@city",
        "userDefined": false
      },
      {
        "text": " at ",
        "userDefined": false
      },
      {
        "text": "8 pm",
        "alias": "datetime",
        "meta": "@sys.date-time",
        "userDefined": false
      }
    ],
    "isTemplate": false,
    "count": 0,
    "updated": 1539785892
  },
  {
    "id": "dbcb4053-a989-4822-9523-40e1b0c65da4",
    "data": [
      {
        "text": "Suggest me some activities in ",
        "userDefined": false
      },
      {
        "text": "December",
        "alias": "datetime",
        "meta": "@sys.date-time",
        "userDefined": false
      },
      {
        "text": " in ",
        "userDefined": false
      },
      {
        "text": "Nice",
        "alias": "city",
        "meta": "@city",
        "userDefined": false
      }
    ],
    "isTemplate": false,
    "count": 0,
    "updated": 1539785892
  },
  {
    "id": "d663edd6-35ee-4804-98f6-5f4e8ea7fe8c",
    "data": [
      {
        "text": "Suggest me some activities ",
        "userDefined": false
      },
      {
        "text": "today",
        "alias": "datetime",
        "meta": "@sys.date-time",
        "userDefined": false
      },
      {
        "text": " in  ",
        "userDefined": false
      },
      {
        "text": "Nice",
        "alias": "city",
        "meta": "@city",
        "userDefined": false
      }
    ],
    "isTemplate": false,
    "count": 0,
    "updated": 1539785892
  },
  {
    "id": "dc32e1fb-e179-4ee8-ae71-54afec68000c",
    "data": [
      {
        "text": "Suggest me some activities in ",
        "userDefined": false
      },
      {
        "text": "Nice",
        "alias": "city",
        "meta": "@city",
        "userDefined": false
      },
      {
        "text": " on ",
        "userDefined": false
      },
      {
        "text": "14th August",
        "alias": "datetime",
        "meta": "@sys.date-time",
        "userDefined": false
      }
    ],
    "isTemplate": false,
    "count": 0,
    "updated": 1539785892
  },
  {
    "id": "7425330e-f919-4209-8e72-6a9831e0f088",
    "data": [
      {
        "text": "Propose me some activities in ",
        "userDefined": false
      },
      {
        "text": "Nice",
        "alias": "city",
        "meta": "@city",
        "userDefined": false
      },
      {
        "text": " at ",
        "userDefined": false
      },
      {
        "text": "8 pm",
        "alias": "datetime",
        "meta": "@sys.date-time",
        "userDefined": false
      }
    ],
    "isTemplate": false,
    "count": 0,
    "updated": 1539785892
  },
  {
    "id": "fdf2e21b-a793-4777-992f-4de720ce67bc",
    "data": [
      {
        "text": "Propose me some activities in ",
        "userDefined": false
      },
      {
        "text": "December",
        "alias": "datetime",
        "meta": "@sys.date-time",
        "userDefined": false
      },
      {
        "text": " in ",
        "userDefined": false
      },
      {
        "text": "Nice",
        "alias": "city",
        "meta": "@city",
        "userDefined": false
      }
    ],
    "isTemplate": false,
    "count": 0,
    "updated": 1539785892
  },
  {
    "id": "5f878d21-64a8-47bb-be5f-2ef043b1ff6d",
    "data": [
      {
        "text": "Propose me some activities ",
        "userDefined": false
      },
      {
        "text": "today",
        "alias": "datetime",
        "meta": "@sys.date-time",
        "userDefined": false
      },
      {
        "text": " in  ",
        "userDefined": false
      },
      {
        "text": "Nice",
        "alias": "city",
        "meta": "@city",
        "userDefined": false
      }
    ],
    "isTemplate": false,
    "count": 0,
    "updated": 1539785892
  },
  {
    "id": "0b89cb8c-6506-48bc-81b4-9fd8ed3c883c",
    "data": [
      {
        "text": "Propose me some activities in ",
        "userDefined": false
      },
      {
        "text": "Nice",
        "alias": "city",
        "meta": "@city",
        "userDefined": false
      },
      {
        "text": " on ",
        "userDefined": false
      },
      {
        "text": "14th August",
        "alias": "datetime",
        "meta": "@sys.date-time",
        "userDefined": false
      }
    ],
    "isTemplate": false,
    "count": 0,
    "updated": 1539785892
  },
  {
    "id": "b0105ae7-f5bd-4e6b-9076-e85fb53fd5f0",
    "data": [
      {
        "text": "find an activity in ",
        "userDefined": false
      },
      {
        "text": "Nice",
        "alias": "city",
        "meta": "@city",
        "userDefined": false
      },
      {
        "text": " at ",
        "userDefined": false
      },
      {
        "text": "8 pm",
        "alias": "datetime",
        "meta": "@sys.date-time",
        "userDefined": false
      }
    ],
    "isTemplate": false,
    "count": 0,
    "updated": 1539785892
  },
  {
    "id": "66fc46f9-1c73-403d-bb98-e2421b8c9799",
    "data": [
      {
        "text": "find an activity in ",
        "userDefined": false
      },
      {
        "text": "December",
        "alias": "datetime",
        "meta": "@sys.date-time",
        "userDefined": false
      },
      {
        "text": " in ",
        "userDefined": false
      },
      {
        "text": "Nice",
        "alias": "city",
        "meta": "@city",
        "userDefined": false
      }
    ],
    "isTemplate": false,
    "count": 0,
    "updated": 1539785892
  },
  {
    "id": "5d7f0c8f-a81b-4592-8bee-90fe02962ce8",
    "data": [
      {
        "text": "find an activity ",
        "userDefined": false
      },
      {
        "text": "today",
        "alias": "datetime",
        "meta": "@sys.date-time",
        "userDefined": false
      },
      {
        "text": " in  ",
        "userDefined": false
      },
      {
        "text": "Nice",
        "alias": "city",
        "meta": "@city",
        "userDefined": false
      }
    ],
    "isTemplate": false,
    "count": 0,
    "updated": 1539785892
  },
  {
    "id": "17f89466-ddfb-41d9-a691-e2819f61ba2d",
    "data": [
      {
        "text": "find an activity in ",
        "userDefined": false
      },
      {
        "text": "Nice",
        "alias": "city",
        "meta": "@city",
        "userDefined": false
      },
      {
        "text": " on ",
        "userDefined": false
      },
      {
        "text": "14th August",
        "alias": "datetime",
        "meta": "@sys.date-time",
        "userDefined": false
      }
    ],
    "isTemplate": false,
    "count": 0,
    "updated": 1539785892
  },
  {
    "id": "8bcdfc2b-04b4-495d-93c3-678e3f75c797",
    "data": [
      {
        "text": "Activity in ",
        "userDefined": false
      },
      {
        "text": "Nice",
        "alias": "city",
        "meta": "@city",
        "userDefined": false
      },
      {
        "text": " at ",
        "userDefined": false
      },
      {
        "text": "8 pm",
        "alias": "datetime",
        "meta": "@sys.date-time",
        "userDefined": false
      }
    ],
    "isTemplate": false,
    "count": 0,
    "updated": 1539785892
  },
  {
    "id": "71943267-e276-4614-a659-1e0bd446a434",
    "data": [
      {
        "text": "Activity in ",
        "userDefined": false
      },
      {
        "text": "December",
        "alias": "datetime",
        "meta": "@sys.date-time",
        "userDefined": false
      },
      {
        "text": " in ",
        "userDefined": false
      },
      {
        "text": "Nice",
        "alias": "city",
        "meta": "@city",
        "userDefined": false
      }
    ],
    "isTemplate": false,
    "count": 0,
    "updated": 1539785892
  },
  {
    "id": "2aef8975-5e22-47c8-9345-b8888ce25472",
    "data": [
      {
        "text": "Activity ",
        "userDefined": false
      },
      {
        "text": "today",
        "alias": "datetime",
        "meta": "@sys.date-time",
        "userDefined": false
      },
      {
        "text": " in  ",
        "userDefined": false
      },
      {
        "text": "Nice",
        "alias": "city",
        "meta": "@city",
        "userDefined": false
      }
    ],
    "isTemplate": false,
    "count": 0,
    "updated": 1539785892
  },
  {
    "id": "7cdb3f06-4b0a-4c61-835d-c2b72f17a285",
    "data": [
      {
        "text": "Activity in ",
        "userDefined": false
      },
      {
        "text": "Nice",
        "alias": "city",
        "meta": "@city",
        "userDefined": false
      },
      {
        "text": " on ",
        "userDefined": false
      },
      {
        "text": "14th August",
        "alias": "datetime",
        "meta": "@sys.date-time",
        "userDefined": false
      }
    ],
    "isTemplate": false,
    "count": 0,
    "updated": 1539785892
  },
  {
    "id": "3c70458d-654b-47af-aa0d-8cc051812ba2",
    "data": [
      {
        "text": "look for some activities in ",
        "userDefined": false
      },
      {
        "text": "Nice",
        "alias": "city",
        "meta": "@city",
        "userDefined": false
      },
      {
        "text": " at ",
        "userDefined": false
      },
      {
        "text": "8 pm",
        "alias": "datetime",
        "meta": "@sys.date-time",
        "userDefined": false
      }
    ],
    "isTemplate": false,
    "count": 0,
    "updated": 1539785892
  },
  {
    "id": "af1a43dd-2af0-40bf-9482-76f122f710e9",
    "data": [
      {
        "text": "look for some activities in ",
        "userDefined": false
      },
      {
        "text": "December",
        "alias": "datetime",
        "meta": "@sys.date-time",
        "userDefined": false
      },
      {
        "text": " in ",
        "userDefined": false
      },
      {
        "text": "Nice",
        "alias": "city",
        "meta": "@city",
        "userDefined": false
      }
    ],
    "isTemplate": false,
    "count": 0,
    "updated": 1539785892
  },
  {
    "id": "fc505a8f-1968-4514-999f-c8339fd162a4",
    "data": [
      {
        "text": "look for some activities ",
        "userDefined": false
      },
      {
        "text": "today",
        "alias": "datetime",
        "meta": "@sys.date-time",
        "userDefined": false
      },
      {
        "text": " in  ",
        "userDefined": false
      },
      {
        "text": "Nice",
        "alias": "city",
        "meta": "@city",
        "userDefined": false
      }
    ],
    "isTemplate": false,
    "count": 0,
    "updated": 1539785892
  },
  {
    "id": "13eda898-cbcb-402c-8428-c0c7c51de7f3",
    "data": [
      {
        "text": "look for some activities in ",
        "userDefined": false
      },
      {
        "text": "Nice",
        "alias": "city",
        "meta": "@city",
        "userDefined": false
      },
      {
        "text": " on ",
        "userDefined": false
      },
      {
        "text": "14th August",
        "alias": "datetime",
        "meta": "@sys.date-time",
        "userDefined": false
      }
    ],
    "isTemplate": false,
    "count": 0,
    "updated": 1539785892
  },
  {
    "id": "2515141e-4b99-4e6b-8f2c-09c9433a2077",
    "data": [
      {
        "text": "show me something to do at ",
        "userDefined": false
      },
      {
        "text": "8 pm",
        "alias": "datetime",
        "meta": "@sys.date-time",
        "userDefined": false
      },
      {
        "text": " in ",
        "userDefined": false
      },
      {
        "text": "Nice",
        "alias": "city",
        "meta": "@city",
        "userDefined": false
      },
      {
        "text": " ",
        "userDefined": false
      }
    ],
    "isTemplate": false,
    "count": 0,
    "updated": 1539785892
  },
  {
    "id": "579eba2f-35b2-4a9a-9787-1a4d468b42ef",
    "data": [
      {
        "text": "Any activities at ",
        "userDefined": false
      },
      {
        "text": "8 pm",
        "alias": "datetime",
        "meta": "@sys.date-time",
        "userDefined": false
      },
      {
        "text": " in ",
        "userDefined": false
      },
      {
        "text": "Nice",
        "alias": "city",
        "meta": "@city",
        "userDefined": false
      }
    ],
    "isTemplate": false,
    "count": 0,
    "updated": 1539785892
  },
  {
    "id": "f861ad9a-91d1-43b4-a9df-b74ce7c0c26d",
    "data": [
      {
        "text": "I\u0027m bored, Suggest me some activities at ",
        "userDefined": false
      },
      {
        "text": "8 pm",
        "alias": "datetime",
        "meta": "@sys.date-time",
        "userDefined": false
      },
      {
        "text": " in ",
        "userDefined": false
      },
      {
        "text": "Nice",
        "alias": "city",
        "meta": "@city",
        "userDefined": false
      }
    ],
    "isTemplate": false,
    "count": 0,
    "updated": 1539785892
  },
  {
    "id": "7aca940b-91a8-46d8-9b70-d152fea4ff12",
    "data": [
      {
        "text": "Find me an activity at ",
        "userDefined": false
      },
      {
        "text": "8 pm",
        "alias": "datetime",
        "meta": "@sys.date-time",
        "userDefined": false
      },
      {
        "text": " in ",
        "userDefined": false
      },
      {
        "text": "Nice",
        "alias": "city",
        "meta": "@city",
        "userDefined": false
      }
    ],
    "isTemplate": false,
    "count": 0,
    "updated": 1539785892
  },
  {
    "id": "e817dfed-f1d9-4c63-aad8-2018335e87c6",
    "data": [
      {
        "text": "Activity in at ",
        "userDefined": false
      },
      {
        "text": "8 pm",
        "alias": "datetime",
        "meta": "@sys.date-time",
        "userDefined": false
      },
      {
        "text": " in ",
        "userDefined": false
      },
      {
        "text": "Nice",
        "alias": "city",
        "meta": "@city",
        "userDefined": false
      }
    ],
    "isTemplate": false,
    "count": 0,
    "updated": 1539785892
  },
  {
    "id": "a4f19a6b-a2ad-4429-b571-47be8614ddcd",
    "data": [
      {
        "text": "check for some activities at ",
        "userDefined": false
      },
      {
        "text": "8 pm",
        "alias": "datetime",
        "meta": "@sys.date-time",
        "userDefined": false
      },
      {
        "text": " in ",
        "userDefined": false
      },
      {
        "text": "Nice",
        "alias": "city",
        "meta": "@city",
        "userDefined": false
      }
    ],
    "isTemplate": false,
    "count": 0,
    "updated": 1539785892
  },
  {
    "id": "ffcf4762-d3c1-4cdd-be43-4beef707fae5",
    "data": [
      {
        "text": "suggest me some activities at ",
        "userDefined": false
      },
      {
        "text": "8 pm",
        "alias": "datetime",
        "meta": "@sys.date-time",
        "userDefined": false
      },
      {
        "text": " in ",
        "userDefined": false
      },
      {
        "text": "Nice",
        "alias": "city",
        "meta": "@city",
        "userDefined": false
      }
    ],
    "isTemplate": false,
    "count": 0,
    "updated": 1539785892
  },
  {
    "id": "16bd8b93-db56-4113-a788-f8a3afa2e582",
    "data": [
      {
        "text": "propose me some activities at ",
        "userDefined": false
      },
      {
        "text": "8 pm",
        "alias": "datetime",
        "meta": "@sys.date-time",
        "userDefined": false
      },
      {
        "text": " in ",
        "userDefined": false
      },
      {
        "text": "Nice",
        "alias": "city",
        "meta": "@city",
        "userDefined": false
      }
    ],
    "isTemplate": false,
    "count": 0,
    "updated": 1539785892
  },
  {
    "id": "10a469fe-10cc-404a-b863-96a358a8e1e0",
    "data": [
      {
        "text": "find an activity at ",
        "userDefined": false
      },
      {
        "text": "8 pm",
        "alias": "datetime",
        "meta": "@sys.date-time",
        "userDefined": false
      },
      {
        "text": " in ",
        "userDefined": false
      },
      {
        "text": "Nice",
        "alias": "city",
        "meta": "@city",
        "userDefined": false
      }
    ],
    "isTemplate": false,
    "count": 0,
    "updated": 1539785892
  },
  {
    "id": "1190a2da-2b79-40b5-b979-b3b4a616b0e5",
    "data": [
      {
        "text": "Look for some activities at ",
        "userDefined": false
      },
      {
        "text": "8 pm",
        "alias": "datetime",
        "meta": "@sys.date-time",
        "userDefined": false
      },
      {
        "text": " in ",
        "userDefined": false
      },
      {
        "text": "Nice",
        "alias": "city",
        "meta": "@city",
        "userDefined": false
      }
    ],
    "isTemplate": false,
    "count": 0,
    "updated": 1539785892
  },
  {
    "id": "5e4a44e5-6d5f-4086-a392-0902ce6e602d",
    "data": [
      {
        "text": "I want to do activity on ",
        "userDefined": false
      },
      {
        "text": "14th August",
        "alias": "datetime",
        "meta": "@sys.date-time",
        "userDefined": false
      },
      {
        "text": " in ",
        "userDefined": false
      },
      {
        "text": "Nice",
        "alias": "city",
        "meta": "@city",
        "userDefined": false
      }
    ],
    "isTemplate": false,
    "count": 0,
    "updated": 1539785892
  },
  {
    "id": "2c587b5d-f0a4-4211-95b7-7fa9f8cb156c",
    "data": [
      {
        "text": "show me something to do on ",
        "userDefined": false
      },
      {
        "text": "14th August",
        "alias": "datetime",
        "meta": "@sys.date-time",
        "userDefined": false
      },
      {
        "text": " in ",
        "userDefined": false
      },
      {
        "text": "Nice",
        "alias": "city",
        "meta": "@city",
        "userDefined": false
      }
    ],
    "isTemplate": false,
    "count": 0,
    "updated": 1539785892
  },
  {
    "id": "84fb4b13-f88d-4ac0-a1f3-5249482855f9",
    "data": [
      {
        "text": "Any activities on ",
        "userDefined": false
      },
      {
        "text": "14th August",
        "alias": "datetime",
        "meta": "@sys.date-time",
        "userDefined": false
      },
      {
        "text": " in ",
        "userDefined": false
      },
      {
        "text": "Nice",
        "alias": "city",
        "meta": "@city",
        "userDefined": false
      }
    ],
    "isTemplate": false,
    "count": 0,
    "updated": 1539785892
  },
  {
    "id": "0b0fe71a-69c0-4fd9-bebe-4bbf3f344a6a",
    "data": [
      {
        "text": "I\u0027m bored, Suggest me some activities on ",
        "userDefined": false
      },
      {
        "text": "14th August",
        "alias": "datetime",
        "meta": "@sys.date-time",
        "userDefined": false
      },
      {
        "text": " in ",
        "userDefined": false
      },
      {
        "text": "Nice",
        "alias": "city",
        "meta": "@city",
        "userDefined": false
      }
    ],
    "isTemplate": false,
    "count": 0,
    "updated": 1539785892
  },
  {
    "id": "1c0c0be1-18a3-409f-a172-cdff29f483e9",
    "data": [
      {
        "text": "Find me an activity on ",
        "userDefined": false
      },
      {
        "text": "14th August",
        "alias": "datetime",
        "meta": "@sys.date-time",
        "userDefined": false
      },
      {
        "text": " in ",
        "userDefined": false
      },
      {
        "text": "Nice",
        "alias": "city",
        "meta": "@city",
        "userDefined": false
      }
    ],
    "isTemplate": false,
    "count": 0,
    "updated": 1539785892
  },
  {
    "id": "c7f7fb16-efbf-4946-ade4-d3a75a138d34",
    "data": [
      {
        "text": "Activity in on ",
        "userDefined": false
      },
      {
        "text": "14th August",
        "alias": "datetime",
        "meta": "@sys.date-time",
        "userDefined": false
      },
      {
        "text": " in ",
        "userDefined": false
      },
      {
        "text": "Nice",
        "alias": "city",
        "meta": "@city",
        "userDefined": false
      }
    ],
    "isTemplate": false,
    "count": 0,
    "updated": 1539785892
  },
  {
    "id": "5535ee0e-872e-4e56-b14d-4ba08cc15061",
    "data": [
      {
        "text": "check for some activities on ",
        "userDefined": false
      },
      {
        "text": "14th August",
        "alias": "datetime",
        "meta": "@sys.date-time",
        "userDefined": false
      },
      {
        "text": " in ",
        "userDefined": false
      },
      {
        "text": "Nice",
        "alias": "city",
        "meta": "@city",
        "userDefined": false
      }
    ],
    "isTemplate": false,
    "count": 0,
    "updated": 1539785892
  },
  {
    "id": "4d40930b-f5d7-4be0-9f48-5f645e7476f9",
    "data": [
      {
        "text": "suggest me some activities on ",
        "userDefined": false
      },
      {
        "text": "14th August",
        "alias": "datetime",
        "meta": "@sys.date-time",
        "userDefined": false
      },
      {
        "text": " in ",
        "userDefined": false
      },
      {
        "text": "Nice",
        "alias": "city",
        "meta": "@city",
        "userDefined": false
      }
    ],
    "isTemplate": false,
    "count": 0,
    "updated": 1539785892
  },
  {
    "id": "de4d35c1-b144-41d2-9bb7-96667fd9b022",
    "data": [
      {
        "text": "propose me some activities on ",
        "userDefined": false
      },
      {
        "text": "14th August",
        "alias": "datetime",
        "meta": "@sys.date-time",
        "userDefined": false
      },
      {
        "text": " in ",
        "userDefined": false
      },
      {
        "text": "Nice",
        "alias": "city",
        "meta": "@city",
        "userDefined": false
      }
    ],
    "isTemplate": false,
    "count": 0,
    "updated": 1539785892
  },
  {
    "id": "d9b2e4e9-de8e-4b6b-b6d7-4bc799610707",
    "data": [
      {
        "text": "find an activity on ",
        "userDefined": false
      },
      {
        "text": "14th August",
        "alias": "datetime",
        "meta": "@sys.date-time",
        "userDefined": false
      },
      {
        "text": " in ",
        "userDefined": false
      },
      {
        "text": "Nice",
        "alias": "city",
        "meta": "@city",
        "userDefined": false
      }
    ],
    "isTemplate": false,
    "count": 0,
    "updated": 1539785892
  },
  {
    "id": "4632eecb-66d2-4f75-b657-22643e893351",
    "data": [
      {
        "text": "Look for some activities on ",
        "userDefined": false
      },
      {
        "text": "14th August",
        "alias": "datetime",
        "meta": "@sys.date-time",
        "userDefined": false
      },
      {
        "text": " in ",
        "userDefined": false
      },
      {
        "text": "Nice",
        "alias": "city",
        "meta": "@city",
        "userDefined": false
      }
    ],
    "isTemplate": false,
    "count": 0,
    "updated": 1539785892
  },
  {
    "id": "ad82b027-a39b-4257-8442-2830297a43e4",
    "data": [
      {
        "text": "what do you want me to do on ",
        "userDefined": false
      },
      {
        "text": "14th August",
        "alias": "datetime",
        "meta": "@sys.date-time",
        "userDefined": false
      },
      {
        "text": " in ",
        "userDefined": false
      },
      {
        "text": "Nice",
        "alias": "city",
        "meta": "@city",
        "userDefined": false
      }
    ],
    "isTemplate": false,
    "count": 0,
    "updated": 1539785892
  },
  {
    "id": "58f237ef-7741-4bda-b526-e0752145725d",
    "data": [
      {
        "text": "where can I find some Water Sports in ",
        "userDefined": false
      },
      {
        "text": "Nice",
        "alias": "city",
        "meta": "@city",
        "userDefined": false
      }
    ],
    "isTemplate": false,
    "count": 0,
    "updated": 1539785892
  },
  {
    "id": "caa04348-7edc-48ba-8ef0-9bbbbb169dae",
    "data": [
      {
        "text": "where can I find some Water Sports in ",
        "userDefined": false
      },
      {
        "text": "Nice",
        "alias": "city",
        "meta": "@city",
        "userDefined": false
      },
      {
        "text": " at ",
        "userDefined": false
      },
      {
        "text": "8 pm",
        "alias": "datetime",
        "meta": "@sys.date-time",
        "userDefined": false
      }
    ],
    "isTemplate": false,
    "count": 0,
    "updated": 1539785892
  },
  {
    "id": "058c9a0e-6d54-448d-a8c1-61eb760eade4",
    "data": [
      {
        "text": "where can I find some Water Sports in ",
        "userDefined": false
      },
      {
        "text": "December",
        "alias": "datetime",
        "meta": "@sys.date-time",
        "userDefined": false
      },
      {
        "text": " in ",
        "userDefined": false
      },
      {
        "text": "Nice",
        "alias": "city",
        "meta": "@city",
        "userDefined": false
      }
    ],
    "isTemplate": false,
    "count": 0,
    "updated": 1539785892
  },
  {
    "id": "acb4e178-61d0-4508-b09e-fc6bb838d661",
    "data": [
      {
        "text": "where can I find some Water Sports ",
        "userDefined": false
      },
      {
        "text": "today",
        "alias": "datetime",
        "meta": "@sys.date-time",
        "userDefined": false
      },
      {
        "text": " in  ",
        "userDefined": false
      },
      {
        "text": "Nice",
        "alias": "city",
        "meta": "@city",
        "userDefined": false
      }
    ],
    "isTemplate": false,
    "count": 0,
    "updated": 1539785892
  },
  {
    "id": "81ff2e92-d19d-4a7f-a48c-dcf67bca68a8",
    "data": [
      {
        "text": "where can I find some Water Sports in ",
        "userDefined": false
      },
      {
        "text": "Nice",
        "alias": "city",
        "meta": "@city",
        "userDefined": false
      },
      {
        "text": " on ",
        "userDefined": false
      },
      {
        "text": "14th August",
        "alias": "datetime",
        "meta": "@sys.date-time",
        "userDefined": false
      }
    ],
    "isTemplate": false,
    "count": 0,
    "updated": 1539785892
  },
  {
    "id": "f98b1014-e8cc-4288-99e9-3a6c0b1725e6",
    "data": [
      {
        "text": "where can I find some Water Sports at ",
        "userDefined": false
      },
      {
        "text": "8 pm",
        "alias": "datetime",
        "meta": "@sys.date-time",
        "userDefined": false
      },
      {
        "text": " in ",
        "userDefined": false
      },
      {
        "text": "Nice",
        "alias": "city",
        "meta": "@city",
        "userDefined": false
      }
    ],
    "isTemplate": false,
    "count": 0,
    "updated": 1539785892
  },
  {
    "id": "e5e9e9cc-f113-4321-b370-bb3509a50322",
    "data": [
      {
        "text": "where can I find some Water Sports on ",
        "userDefined": false
      },
      {
        "text": "14th August",
        "alias": "datetime",
        "meta": "@sys.date-time",
        "userDefined": false
      },
      {
        "text": " in ",
        "userDefined": false
      },
      {
        "text": "Nice",
        "alias": "city",
        "meta": "@city",
        "userDefined": false
      }
    ],
    "isTemplate": false,
    "count": 0,
    "updated": 1539785892
  },
  {
    "id": "615786f8-9398-4b88-ad33-2c5bb95c7084",
    "data": [
      {
        "text": "I want to do activity in ",
        "userDefined": false
      },
      {
        "text": "today",
        "alias": "datetime",
        "meta": "@sys.date-time",
        "userDefined": false
      },
      {
        "text": " ",
        "userDefined": false
      },
      {
        "text": "Nice",
        "alias": "city",
        "meta": "@city",
        "userDefined": false
      }
    ],
    "isTemplate": false,
    "count": 0,
    "updated": 1539785892
  },
  {
    "id": "ba166fc5-a2d2-4f88-8a37-6a2d16dec408",
    "data": [
      {
        "text": "Show me something to do ",
        "userDefined": false
      },
      {
        "text": "today",
        "alias": "datetime",
        "meta": "@sys.date-time",
        "userDefined": false
      },
      {
        "text": " ",
        "userDefined": false
      },
      {
        "text": "Nice",
        "alias": "city",
        "meta": "@city",
        "userDefined": false
      }
    ],
    "isTemplate": false,
    "count": 0,
    "updated": 1539785892
  },
  {
    "id": "2704a9d3-d566-4098-9a7a-41e152164cb1",
    "data": [
      {
        "text": "Any activities in  ",
        "userDefined": false
      },
      {
        "text": "today",
        "alias": "datetime",
        "meta": "@sys.date-time",
        "userDefined": false
      },
      {
        "text": " ",
        "userDefined": false
      },
      {
        "text": "Nice",
        "alias": "city",
        "meta": "@city",
        "userDefined": false
      }
    ],
    "isTemplate": false,
    "count": 0,
    "updated": 1539785892
  },
  {
    "id": "ffa69dd3-f089-46d9-a013-84f0c6d43c05",
    "data": [
      {
        "text": "I\u0027m bored, suggest me some activities on ",
        "userDefined": false
      },
      {
        "text": "today",
        "alias": "datetime",
        "meta": "@sys.date-time",
        "userDefined": false
      },
      {
        "text": " ",
        "userDefined": false
      },
      {
        "text": "Nice",
        "alias": "city",
        "meta": "@city",
        "userDefined": false
      }
    ],
    "isTemplate": false,
    "count": 0,
    "updated": 1539785892
  },
  {
    "id": "05280809-94cb-4042-98c6-9787ec09875d",
    "data": [
      {
        "text": "Find me an activity ",
        "userDefined": false
      },
      {
        "text": "today",
        "alias": "datetime",
        "meta": "@sys.date-time",
        "userDefined": false
      },
      {
        "text": " ",
        "userDefined": false
      },
      {
        "text": "Nice",
        "alias": "city",
        "meta": "@city",
        "userDefined": false
      }
    ],
    "isTemplate": false,
    "count": 0,
    "updated": 1539785892
  },
  {
    "id": "32c01e31-80f4-49c3-9bbf-d61f4ecbd96c",
    "data": [
      {
        "text": "Activity in  ",
        "userDefined": false
      },
      {
        "text": "today",
        "alias": "datetime",
        "meta": "@sys.date-time",
        "userDefined": false
      },
      {
        "text": " ",
        "userDefined": false
      },
      {
        "text": "Nice",
        "alias": "city",
        "meta": "@city",
        "userDefined": false
      }
    ],
    "isTemplate": false,
    "count": 0,
    "updated": 1539785892
  },
  {
    "id": "e8406a7e-cd77-4c60-867d-4a0ea7ef410f",
    "data": [
      {
        "text": "check for some activities ",
        "userDefined": false
      },
      {
        "text": "today",
        "alias": "datetime",
        "meta": "@sys.date-time",
        "userDefined": false
      },
      {
        "text": " ",
        "userDefined": false
      },
      {
        "text": "Nice",
        "alias": "city",
        "meta": "@city",
        "userDefined": false
      }
    ],
    "isTemplate": false,
    "count": 0,
    "updated": 1539785892
  },
  {
    "id": "ca2879a3-f631-4234-8a80-5006adef0866",
    "data": [
      {
        "text": "Suggest me some activities ",
        "userDefined": false
      },
      {
        "text": "today",
        "alias": "datetime",
        "meta": "@sys.date-time",
        "userDefined": false
      },
      {
        "text": " ",
        "userDefined": false
      },
      {
        "text": "Nice",
        "alias": "city",
        "meta": "@city",
        "userDefined": false
      }
    ],
    "isTemplate": false,
    "count": 0,
    "updated": 1539785892
  },
  {
    "id": "1c96cf54-b75d-439e-a716-609776452356",
    "data": [
      {
        "text": "Propose me some activities ",
        "userDefined": false
      },
      {
        "text": "today",
        "alias": "datetime",
        "meta": "@sys.date-time",
        "userDefined": false
      },
      {
        "text": " ",
        "userDefined": false
      },
      {
        "text": "Nice",
        "alias": "city",
        "meta": "@city",
        "userDefined": false
      }
    ],
    "isTemplate": false,
    "count": 0,
    "updated": 1539785892
  },
  {
    "id": "13d31a42-4f52-4517-b36d-d02f75b71555",
    "data": [
      {
        "text": "find an activity ",
        "userDefined": false
      },
      {
        "text": "today",
        "alias": "datetime",
        "meta": "@sys.date-time",
        "userDefined": false
      },
      {
        "text": " ",
        "userDefined": false
      },
      {
        "text": "Nice",
        "alias": "city",
        "meta": "@city",
        "userDefined": false
      }
    ],
    "isTemplate": false,
    "count": 0,
    "updated": 1539785892
  },
  {
    "id": "4d08e77f-4a8c-4b25-be11-a63255c28741",
    "data": [
      {
        "text": "look for some activities ",
        "userDefined": false
      },
      {
        "text": "today",
        "alias": "datetime",
        "meta": "@sys.date-time",
        "userDefined": false
      },
      {
        "text": " ",
        "userDefined": false
      },
      {
        "text": "Nice",
        "alias": "city",
        "meta": "@city",
        "userDefined": false
      }
    ],
    "isTemplate": false,
    "count": 0,
    "updated": 1539785892
  },
  {
    "id": "0880142f-3c8e-4520-8466-92ffc5d81646",
    "data": [
      {
        "text": "where can I find some Water Sports ",
        "userDefined": false
      },
      {
        "text": "today",
        "alias": "datetime",
        "meta": "@sys.date-time",
        "userDefined": false
      },
      {
        "text": " ",
        "userDefined": false
      },
      {
        "text": "Nice",
        "alias": "city",
        "meta": "@city",
        "userDefined": false
      }
    ],
    "isTemplate": false,
    "count": 0,
    "updated": 1539785892
  },
  {
    "id": "e5c74bdc-e4ba-4bf3-b77d-ed724a49cd7c",
    "data": [
      {
        "text": "Activity ",
        "userDefined": false
      },
      {
        "text": "today",
        "alias": "datetime",
        "meta": "@sys.date-time",
        "userDefined": false
      },
      {
        "text": " ",
        "userDefined": false
      },
      {
        "text": "Nice",
        "alias": "city",
        "meta": "@city",
        "userDefined": false
      }
    ],
    "isTemplate": false,
    "count": 0,
    "updated": 1539785892
  },
  {
    "id": "a2273d67-fd34-4f43-a342-7212e2a5a04d",
    "data": [
      {
        "text": "I wanna do activity in ",
        "userDefined": false
      },
      {
        "text": "Nice",
        "alias": "city",
        "meta": "@city",
        "userDefined": false
      },
      {
        "text": " at ",
        "userDefined": false
      },
      {
        "text": "8 pm",
        "alias": "datetime",
        "meta": "@sys.date-time",
        "userDefined": false
      }
    ],
    "isTemplate": false,
    "count": 0,
    "updated": 1539785892
  },
  {
    "id": "b8245e6b-6840-45ac-a25d-a18d433b9a8b",
    "data": [
      {
        "text": "I wanna do activity in ",
        "userDefined": false
      },
      {
        "text": "December",
        "alias": "datetime",
        "meta": "@sys.date-time",
        "userDefined": false
      },
      {
        "text": " in ",
        "userDefined": false
      },
      {
        "text": "Nice",
        "alias": "city",
        "meta": "@city",
        "userDefined": false
      }
    ],
    "isTemplate": false,
    "count": 0,
    "updated": 1539785892
  },
  {
    "id": "07513d05-924e-4414-86e0-aa21854d91cd",
    "data": [
      {
        "text": "I wanna do activity in ",
        "userDefined": false
      },
      {
        "text": "today",
        "alias": "datetime",
        "meta": "@sys.date-time",
        "userDefined": false
      },
      {
        "text": " in  ",
        "userDefined": false
      },
      {
        "text": "Nice",
        "alias": "city",
        "meta": "@city",
        "userDefined": false
      }
    ],
    "isTemplate": false,
    "count": 0,
    "updated": 1539785892
  },
  {
    "id": "49d97bb0-09e4-4484-a480-91a2bb9cd957",
    "data": [
      {
        "text": "I wanna do activity in ",
        "userDefined": false
      },
      {
        "text": "Nice",
        "alias": "city",
        "meta": "@city",
        "userDefined": false
      },
      {
        "text": " on ",
        "userDefined": false
      },
      {
        "text": "14th August",
        "alias": "datetime",
        "meta": "@sys.date-time",
        "userDefined": false
      }
    ],
    "isTemplate": false,
    "count": 0,
    "updated": 1539785892
  },
  {
    "id": "e01063d7-ebd8-4c04-9802-351287614abe",
    "data": [
      {
        "text": "I wanna do activity at ",
        "userDefined": false
      },
      {
        "text": "8 pm",
        "alias": "datetime",
        "meta": "@sys.date-time",
        "userDefined": false
      },
      {
        "text": " in ",
        "userDefined": false
      },
      {
        "text": "Nice",
        "alias": "city",
        "meta": "@city",
        "userDefined": false
      },
      {
        "text": " ",
        "userDefined": false
      }
    ],
    "isTemplate": false,
    "count": 0,
    "updated": 1539785892
  },
  {
    "id": "a7e70bf2-c751-4df0-8474-f11ee4694214",
    "data": [
      {
        "text": "I wanna do activity on ",
        "userDefined": false
      },
      {
        "text": "14th August",
        "alias": "datetime",
        "meta": "@sys.date-time",
        "userDefined": false
      },
      {
        "text": " in ",
        "userDefined": false
      },
      {
        "text": "Nice",
        "alias": "city",
        "meta": "@city",
        "userDefined": false
      }
    ],
    "isTemplate": false,
    "count": 0,
    "updated": 1539785892
  },
  {
    "id": "77e21aae-2752-4f6b-8911-f7a972ddb11f",
    "data": [
      {
        "text": "I wanna do activity in ",
        "userDefined": false
      },
      {
        "text": "today",
        "alias": "datetime",
        "meta": "@sys.date-time",
        "userDefined": false
      },
      {
        "text": " ",
        "userDefined": false
      },
      {
        "text": "Nice",
        "alias": "city",
        "meta": "@city",
        "userDefined": false
      }
    ],
    "isTemplate": false,
    "count": 0,
    "updated": 1539785892
  },
  {
    "id": "5b1654ed-15e8-4444-b0d8-a3ebc9030581",
    "data": [
      {
        "text": "Show me something 2 do ",
        "userDefined": false
      },
      {
        "text": "Nice",
        "alias": "city",
        "meta": "@city",
        "userDefined": false
      },
      {
        "text": " at ",
        "userDefined": false
      },
      {
        "text": "8 pm",
        "alias": "datetime",
        "meta": "@sys.date-time",
        "userDefined": false
      }
    ],
    "isTemplate": false,
    "count": 0,
    "updated": 1539785892
  },
  {
    "id": "35982ab5-d1c1-4ba6-84cf-4c9a1145a598",
    "data": [
      {
        "text": "Show me something 2 do  ",
        "userDefined": false
      },
      {
        "text": "December",
        "alias": "datetime",
        "meta": "@sys.date-time",
        "userDefined": false
      },
      {
        "text": " in ",
        "userDefined": false
      },
      {
        "text": "Nice",
        "alias": "city",
        "meta": "@city",
        "userDefined": false
      }
    ],
    "isTemplate": false,
    "count": 0,
    "updated": 1539785892
  },
  {
    "id": "2d424e4a-1036-458b-8b4d-c7468faca854",
    "data": [
      {
        "text": "Show me something 2 do ",
        "userDefined": false
      },
      {
        "text": "today",
        "alias": "datetime",
        "meta": "@sys.date-time",
        "userDefined": false
      },
      {
        "text": " in  ",
        "userDefined": false
      },
      {
        "text": "Nice",
        "alias": "city",
        "meta": "@city",
        "userDefined": false
      }
    ],
    "isTemplate": false,
    "count": 0,
    "updated": 1539785892
  },
  {
    "id": "bd19d159-1771-45d7-b2ea-41f1dd031b24",
    "data": [
      {
        "text": "Show me something 2 do  ",
        "userDefined": false
      },
      {
        "text": "Nice",
        "alias": "city",
        "meta": "@city",
        "userDefined": false
      },
      {
        "text": " on ",
        "userDefined": false
      },
      {
        "text": "14th August",
        "alias": "datetime",
        "meta": "@sys.date-time",
        "userDefined": false
      }
    ],
    "isTemplate": false,
    "count": 0,
    "updated": 1539785892
  },
  {
    "id": "9feaeca5-5ad3-4419-afbc-f9810c586649",
    "data": [
      {
        "text": "check for  activities on ",
        "userDefined": false
      },
      {
        "text": "14th August",
        "alias": "datetime",
        "meta": "@sys.date-time",
        "userDefined": false
      },
      {
        "text": " in ",
        "userDefined": false
      },
      {
        "text": "Nice",
        "alias": "city",
        "meta": "@city",
        "userDefined": false
      }
    ],
    "isTemplate": false,
    "count": 0,
    "updated": 1539785892
  },
  {
    "id": "975bb81a-1c9c-492b-af90-44be9bd8b3e3",
    "data": [
      {
        "text": "check for  activities ",
        "userDefined": false
      },
      {
        "text": "today",
        "alias": "datetime",
        "meta": "@sys.date-time",
        "userDefined": false
      },
      {
        "text": " ",
        "userDefined": false
      },
      {
        "text": "Nice",
        "alias": "city",
        "meta": "@city",
        "userDefined": false
      }
    ],
    "isTemplate": false,
    "count": 0,
    "updated": 1539785892
  },
  {
    "id": "e322f032-4374-4496-8d0d-b4a9d27929e9",
    "data": [
      {
        "text": "check for  activities at ",
        "userDefined": false
      },
      {
        "text": "8 pm",
        "alias": "datetime",
        "meta": "@sys.date-time",
        "userDefined": false
      },
      {
        "text": " in ",
        "userDefined": false
      },
      {
        "text": "Nice",
        "alias": "city",
        "meta": "@city",
        "userDefined": false
      }
    ],
    "isTemplate": false,
    "count": 0,
    "updated": 1539785892
  },
  {
    "id": "1d41de3e-09e1-47e6-bbd3-ab2f915f4345",
    "data": [
      {
        "text": "check for  activities in ",
        "userDefined": false
      },
      {
        "text": "Nice",
        "alias": "city",
        "meta": "@city",
        "userDefined": false
      },
      {
        "text": " at ",
        "userDefined": false
      },
      {
        "text": "8 pm",
        "alias": "datetime",
        "meta": "@sys.date-time",
        "userDefined": false
      }
    ],
    "isTemplate": false,
    "count": 0,
    "updated": 1539785892
  },
  {
    "id": "48ee5a52-4bf6-4bd6-a94e-50ba1eb5b2be",
    "data": [
      {
        "text": "check for  activities in ",
        "userDefined": false
      },
      {
        "text": "December",
        "alias": "datetime",
        "meta": "@sys.date-time",
        "userDefined": false
      },
      {
        "text": " in ",
        "userDefined": false
      },
      {
        "text": "Nice",
        "alias": "city",
        "meta": "@city",
        "userDefined": false
      }
    ],
    "isTemplate": false,
    "count": 0,
    "updated": 1539785892
  },
  {
    "id": "b4bb6ca4-3526-4c1f-8bfd-812393a2ed6c",
    "data": [
      {
        "text": "check for  activities ",
        "userDefined": false
      },
      {
        "text": "today",
        "alias": "datetime",
        "meta": "@sys.date-time",
        "userDefined": false
      },
      {
        "text": " in  ",
        "userDefined": false
      },
      {
        "text": "Nice",
        "alias": "city",
        "meta": "@city",
        "userDefined": false
      }
    ],
    "isTemplate": false,
    "count": 0,
    "updated": 1539785892
  },
  {
    "id": "8d699365-ca64-42fe-9de0-3eb715eecb3f",
    "data": [
      {
        "text": "check for  activities in ",
        "userDefined": false
      },
      {
        "text": "Nice",
        "alias": "city",
        "meta": "@city",
        "userDefined": false
      },
      {
        "text": " on ",
        "userDefined": false
      },
      {
        "text": "14th August",
        "alias": "datetime",
        "meta": "@sys.date-time",
        "userDefined": false
      }
    ],
    "isTemplate": false,
    "count": 0,
    "updated": 1539785892
  },
  {
    "id": "76f18530-37a3-466a-842e-c83d64ee8957",
    "data": [
      {
        "text": "@activity:activity",
        "userDefined": false
      }
    ],
    "isTemplate": true,
    "count": 0,
    "updated": 1539785892
  },
  {
    "id": "798271ac-be95-4332-88af-41f92b4bfc3e",
    "data": [
      {
        "text": "@sys.any:any @activity:activity",
        "userDefined": false
      }
    ],
    "isTemplate": true,
    "count": 0,
    "updated": 1539785892
  },
  {
    "id": "6a4d7911-de3f-4749-a50f-050df008a38a",
    "data": [
      {
        "text": "@activity:activity @sys.any:any",
        "userDefined": false
      }
    ],
    "isTemplate": true,
    "count": 0,
    "updated": 1539785892
  },
  {
    "id": "cc9b1364-35a9-48f9-97c7-46c84c0ce3c4",
    "data": [
      {
        "text": "@sys.any:any @activity:activity @sys.any:any",
        "userDefined": false
      }
    ],
    "isTemplate": true,
    "count": 0,
    "updated": 1539785892
  },
  {
    "id": "e2a0efb7-9005-4348-ad7d-e73227660c78",
    "data": [
      {
        "text": "@city:city @activity:activity",
        "userDefined": false
      }
    ],
    "isTemplate": true,
    "count": 0,
    "updated": 1539785892
  },
  {
    "id": "d56f06be-4a06-4988-a6d0-7fd73e5d443f",
    "data": [
      {
        "text": "@sys.any:any @city:city @activity:activity",
        "userDefined": false
      }
    ],
    "isTemplate": true,
    "count": 0,
    "updated": 1539785892
  },
  {
    "id": "6426e96a-8235-43ad-8909-f6a3ca6f16c6",
    "data": [
      {
        "text": "@city:city @sys.any:any @activity:activity",
        "userDefined": false
      }
    ],
    "isTemplate": true,
    "count": 0,
    "updated": 1539785892
  },
  {
    "id": "74b1ad8c-2f7b-4e2b-920d-b5e5e97750e3",
    "data": [
      {
        "text": "@city:city @activity:activity @sys.any:any",
        "userDefined": false
      }
    ],
    "isTemplate": true,
    "count": 0,
    "updated": 1539785892
  },
  {
    "id": "73cb77a2-64e5-4b71-b05c-b564f534e58c",
    "data": [
      {
        "text": "@sys.any:any @city:city @sys.any:any @activity:activity",
        "userDefined": false
      }
    ],
    "isTemplate": true,
    "count": 0,
    "updated": 1539785892
  },
  {
    "id": "0640bb79-fe7e-4ea0-a594-398fdaff002c",
    "data": [
      {
        "text": "@sys.any:any @city:city @activity:activity @sys.any:any",
        "userDefined": false
      }
    ],
    "isTemplate": true,
    "count": 0,
    "updated": 1539785892
  },
  {
    "id": "23f562cf-c81a-4c81-b4e4-71bbf60296c1",
    "data": [
      {
        "text": "@city:city @sys.any:any @activity:activity @sys.any:any",
        "userDefined": false
      }
    ],
    "isTemplate": true,
    "count": 0,
    "updated": 1539785892
  },
  {
    "id": "949d099a-045d-4f6d-9f08-3f6bd3ca2d49",
    "data": [
      {
        "text": "@sys.any:any @city:city @sys.any:any @activity:activity @sys.any:any",
        "userDefined": false
      }
    ],
    "isTemplate": true,
    "count": 0,
    "updated": 1539785892
  },
  {
    "id": "4483240c-50de-46db-8d32-54f696360b5b",
    "data": [
      {
        "text": "@activity:activity @city:city",
        "userDefined": false
      }
    ],
    "isTemplate": true,
    "count": 0,
    "updated": 1539785892
  },
  {
    "id": "d520356e-146f-4b58-8fd7-09d8d31c557e",
    "data": [
      {
        "text": "@sys.any:any @activity:activity @city:city",
        "userDefined": false
      }
    ],
    "isTemplate": true,
    "count": 0,
    "updated": 1539785892
  },
  {
    "id": "0c963ea2-ac5c-4531-b4e2-2a7443c2cd99",
    "data": [
      {
        "text": "@activity:activity @sys.any:any @city:city",
        "userDefined": false
      }
    ],
    "isTemplate": true,
    "count": 0,
    "updated": 1539785892
  },
  {
    "id": "3238055e-78ed-498f-8b3d-ff285ed4e1e2",
    "data": [
      {
        "text": "@activity:activity @city:city @sys.any:any",
        "userDefined": false
      }
    ],
    "isTemplate": true,
    "count": 0,
    "updated": 1539785892
  },
  {
    "id": "0f0346e9-5de0-43aa-8118-7052a27bce61",
    "data": [
      {
        "text": "@sys.any:any @activity:activity @sys.any:any @city:city",
        "userDefined": false
      }
    ],
    "isTemplate": true,
    "count": 0,
    "updated": 1539785892
  },
  {
    "id": "35f14db8-50e1-4bd3-ab76-6755990f9006",
    "data": [
      {
        "text": "@sys.any:any @activity:activity @city:city @sys.any:any",
        "userDefined": false
      }
    ],
    "isTemplate": true,
    "count": 0,
    "updated": 1539785892
  },
  {
    "id": "8fb9d5b4-1b8f-434b-a149-686b2d84b927",
    "data": [
      {
        "text": "@activity:activity @sys.any:any @city:city @sys.any:any",
        "userDefined": false
      }
    ],
    "isTemplate": true,
    "count": 0,
    "updated": 1539785892
  },
  {
    "id": "46da2e6f-221e-4902-86b0-bb846b09d4c1",
    "data": [
      {
        "text": "@sys.any:any @activity:activity @sys.any:any @city:city @sys.any:any",
        "userDefined": false
      }
    ],
    "isTemplate": true,
    "count": 0,
    "updated": 1539785892
  },
  {
    "id": "4ae7aa9c-7c03-463a-b32a-9e5a8e62c6da",
    "data": [
      {
        "text": "@sys.date-time:datetime @activity:activity",
        "userDefined": false
      }
    ],
    "isTemplate": true,
    "count": 0,
    "updated": 1539785892
  },
  {
    "id": "39c95835-c5e8-430d-8c80-4ca49beefcbb",
    "data": [
      {
        "text": "@sys.any:any @sys.date-time:datetime @activity:activity",
        "userDefined": false
      }
    ],
    "isTemplate": true,
    "count": 0,
    "updated": 1539785892
  },
  {
    "id": "d1035e86-a2b1-47e9-abd3-b9cb6261d12a",
    "data": [
      {
        "text": "@sys.date-time:datetime @sys.any:any @activity:activity",
        "userDefined": false
      }
    ],
    "isTemplate": true,
    "count": 0,
    "updated": 1539785892
  },
  {
    "id": "d88e8672-d390-4fdf-a28d-0aa53f95e71b",
    "data": [
      {
        "text": "@sys.date-time:datetime @activity:activity @sys.any:any",
        "userDefined": false
      }
    ],
    "isTemplate": true,
    "count": 0,
    "updated": 1539785892
  },
  {
    "id": "6e8f4b20-8be6-4749-a259-2764201af845",
    "data": [
      {
        "text": "@sys.any:any @sys.date-time:datetime @sys.any:any @activity:activity",
        "userDefined": false
      }
    ],
    "isTemplate": true,
    "count": 0,
    "updated": 1539785892
  },
  {
    "id": "a14949ba-6009-4b23-a607-9a02b0e179b3",
    "data": [
      {
        "text": "@sys.any:any @sys.date-time:datetime @activity:activity @sys.any:any",
        "userDefined": false
      }
    ],
    "isTemplate": true,
    "count": 0,
    "updated": 1539785892
  },
  {
    "id": "edee1068-d246-412a-8e1b-f92ba74c51be",
    "data": [
      {
        "text": "@sys.date-time:datetime @sys.any:any @activity:activity @sys.any:any",
        "userDefined": false
      }
    ],
    "isTemplate": true,
    "count": 0,
    "updated": 1539785892
  },
  {
    "id": "d6a58e2c-081f-4f50-8076-ef195c48deaa",
    "data": [
      {
        "text": "@sys.any:any @sys.date-time:datetime @sys.any:any @activity:activity @sys.any:any",
        "userDefined": false
      }
    ],
    "isTemplate": true,
    "count": 0,
    "updated": 1539785892
  },
  {
    "id": "7bcb18ff-db9a-4e83-9287-80ab8d460ee8",
    "data": [
      {
        "text": "@activity:activity @sys.date-time:datetime",
        "userDefined": false
      }
    ],
    "isTemplate": true,
    "count": 0,
    "updated": 1539785892
  },
  {
    "id": "73d8fabe-4fc2-4838-8107-ecf0f35a42d4",
    "data": [
      {
        "text": "@sys.any:any @activity:activity @sys.date-time:datetime",
        "userDefined": false
      }
    ],
    "isTemplate": true,
    "count": 0,
    "updated": 1539785892
  },
  {
    "id": "9866c53c-2129-4562-8eb8-af492b3e2818",
    "data": [
      {
        "text": "@activity:activity @sys.any:any @sys.date-time:datetime",
        "userDefined": false
      }
    ],
    "isTemplate": true,
    "count": 0,
    "updated": 1539785892
  },
  {
    "id": "28883c9e-4a08-43da-bc92-73ee11ee556e",
    "data": [
      {
        "text": "@activity:activity @sys.date-time:datetime @sys.any:any",
        "userDefined": false
      }
    ],
    "isTemplate": true,
    "count": 0,
    "updated": 1539785892
  },
  {
    "id": "fbc13692-375d-4906-8167-ece069760dcb",
    "data": [
      {
        "text": "@sys.any:any @activity:activity @sys.any:any @sys.date-time:datetime",
        "userDefined": false
      }
    ],
    "isTemplate": true,
    "count": 0,
    "updated": 1539785892
  },
  {
    "id": "89f83b76-13ff-4f6a-9726-a2d3e752cbad",
    "data": [
      {
        "text": "@sys.any:any @activity:activity @sys.date-time:datetime @sys.any:any",
        "userDefined": false
      }
    ],
    "isTemplate": true,
    "count": 0,
    "updated": 1539785892
  },
  {
    "id": "06d43b1d-9817-4140-90ee-7ad537c8e86d",
    "data": [
      {
        "text": "@activity:activity @sys.any:any @sys.date-time:datetime @sys.any:any",
        "userDefined": false
      }
    ],
    "isTemplate": true,
    "count": 0,
    "updated": 1539785892
  },
  {
    "id": "d3a2a52d-87c9-4a73-9bba-e53984b26ef8",
    "data": [
      {
        "text": "@sys.any:any @activity:activity @sys.any:any @sys.date-time:datetime @sys.any:any",
        "userDefined": false
      }
    ],
    "isTemplate": true,
    "count": 0,
    "updated": 1539785892
  },
  {
    "id": "d1414746-bb44-40ea-b8c0-4e9620e92265",
    "data": [
      {
        "text": "@city:city @sys.date-time:datetime @activity:activity",
        "userDefined": false
      }
    ],
    "isTemplate": true,
    "count": 0,
    "updated": 1539785892
  },
  {
    "id": "2bd071cd-a14e-4656-bab5-d4ba9af8fac5",
    "data": [
      {
        "text": "@sys.any:any @city:city @sys.date-time:datetime @activity:activity",
        "userDefined": false
      }
    ],
    "isTemplate": true,
    "count": 0,
    "updated": 1539785892
  },
  {
    "id": "f07a67ba-2587-4892-af08-4bea9dedb957",
    "data": [
      {
        "text": "@city:city @sys.any:any @sys.date-time:datetime @activity:activity",
        "userDefined": false
      }
    ],
    "isTemplate": true,
    "count": 0,
    "updated": 1539785892
  },
  {
    "id": "1798965a-86dc-421a-8dde-5aeaca39e56b",
    "data": [
      {
        "text": "@city:city @sys.date-time:datetime @sys.any:any @activity:activity",
        "userDefined": false
      }
    ],
    "isTemplate": true,
    "count": 0,
    "updated": 1539785892
  },
  {
    "id": "f4db773e-23b9-4d4b-a03b-dc8508cd1cf8",
    "data": [
      {
        "text": "@city:city @sys.date-time:datetime @activity:activity @sys.any:any",
        "userDefined": false
      }
    ],
    "isTemplate": true,
    "count": 0,
    "updated": 1539785892
  },
  {
    "id": "0ad51ebe-2bcd-4da7-b3b4-eccf7a207f22",
    "data": [
      {
        "text": "@sys.any:any @city:city @sys.any:any @sys.date-time:datetime @activity:activity",
        "userDefined": false
      }
    ],
    "isTemplate": true,
    "count": 0,
    "updated": 1539785892
  },
  {
    "id": "e71c655d-ab28-4e61-9b30-68713851599e",
    "data": [
      {
        "text": "@sys.any:any @city:city @sys.date-time:datetime @sys.any:any @activity:activity",
        "userDefined": false
      }
    ],
    "isTemplate": true,
    "count": 0,
    "updated": 1539785892
  },
  {
    "id": "8d2aa8ed-2024-4c58-b852-22a7bf75908c",
    "data": [
      {
        "text": "@sys.any:any @city:city @sys.date-time:datetime @activity:activity @sys.any:any",
        "userDefined": false
      }
    ],
    "isTemplate": true,
    "count": 0,
    "updated": 1539785892
  },
  {
    "id": "51e7a0c2-87c5-49ab-a836-bfbc2ff7256e",
    "data": [
      {
        "text": "@city:city @sys.any:any @sys.date-time:datetime @activity:activity @sys.any:any",
        "userDefined": false
      }
    ],
    "isTemplate": true,
    "count": 0,
    "updated": 1539785892
  },
  {
    "id": "df5520e1-9ed2-45eb-bd3e-2f30b47ab0b2",
    "data": [
      {
        "text": "@city:city @sys.date-time:datetime @sys.any:any @activity:activity @sys.any:any",
        "userDefined": false
      }
    ],
    "isTemplate": true,
    "count": 0,
    "updated": 1539785892
  },
  {
    "id": "a99902d2-3d9f-472b-a57c-c83183cb78ae",
    "data": [
      {
        "text": "@sys.any:any @city:city @sys.any:any @sys.date-time:datetime @sys.any:any @activity:activity",
        "userDefined": false
      }
    ],
    "isTemplate": true,
    "count": 0,
    "updated": 1539785892
  },
  {
    "id": "8a7e7f40-b1e7-4f6e-889c-c89bb53001de",
    "data": [
      {
        "text": "@sys.any:any @city:city @sys.any:any @sys.date-time:datetime @activity:activity @sys.any:any",
        "userDefined": false
      }
    ],
    "isTemplate": true,
    "count": 0,
    "updated": 1539785892
  },
  {
    "id": "8e370f25-0ddc-4b40-8aa4-1eb6c9ca9c72",
    "data": [
      {
        "text": "@sys.any:any @city:city @sys.date-time:datetime @sys.any:any @activity:activity @sys.any:any",
        "userDefined": false
      }
    ],
    "isTemplate": true,
    "count": 0,
    "updated": 1539785892
  },
  {
    "id": "91ba8b32-ca5a-4ccf-bb78-9639cdb5d22c",
    "data": [
      {
        "text": "@city:city @sys.any:any @sys.date-time:datetime @sys.any:any @activity:activity @sys.any:any",
        "userDefined": false
      }
    ],
    "isTemplate": true,
    "count": 0,
    "updated": 1539785892
  },
  {
    "id": "578850d4-11d1-4a99-9f8e-8855dc921745",
    "data": [
      {
        "text": "@sys.any:any @city:city @sys.any:any @sys.date-time:datetime @sys.any:any @activity:activity @sys.any:any",
        "userDefined": false
      }
    ],
    "isTemplate": true,
    "count": 0,
    "updated": 1539785892
  },
  {
    "id": "180c1e60-9832-4063-a811-c50f7c91f2cf",
    "data": [
      {
        "text": "@city:city @activity:activity @sys.date-time:datetime",
        "userDefined": false
      }
    ],
    "isTemplate": true,
    "count": 0,
    "updated": 1539785892
  },
  {
    "id": "31db223a-4a61-49ca-a0a7-71deb4630bf1",
    "data": [
      {
        "text": "@sys.any:any @city:city @activity:activity @sys.date-time:datetime",
        "userDefined": false
      }
    ],
    "isTemplate": true,
    "count": 0,
    "updated": 1539785892
  },
  {
    "id": "e5972d9f-8c01-410b-995d-256d86502941",
    "data": [
      {
        "text": "@city:city @sys.any:any @activity:activity @sys.date-time:datetime",
        "userDefined": false
      }
    ],
    "isTemplate": true,
    "count": 0,
    "updated": 1539785892
  },
  {
    "id": "e70b61a8-c5f4-447a-8def-1b1fd95427e4",
    "data": [
      {
        "text": "@city:city @activity:activity @sys.any:any @sys.date-time:datetime",
        "userDefined": false
      }
    ],
    "isTemplate": true,
    "count": 0,
    "updated": 1539785892
  },
  {
    "id": "206b7998-366b-497e-af94-22ce9b2d0543",
    "data": [
      {
        "text": "@city:city @activity:activity @sys.date-time:datetime @sys.any:any",
        "userDefined": false
      }
    ],
    "isTemplate": true,
    "count": 0,
    "updated": 1539785892
  },
  {
    "id": "8092248f-c05a-4c81-9fb9-e89eeb2a2388",
    "data": [
      {
        "text": "@sys.any:any @city:city @sys.any:any @activity:activity @sys.date-time:datetime",
        "userDefined": false
      }
    ],
    "isTemplate": true,
    "count": 0,
    "updated": 1539785892
  },
  {
    "id": "7db4c004-45bd-4812-a5ed-e9a34e52c48d",
    "data": [
      {
        "text": "@sys.any:any @city:city @activity:activity @sys.any:any @sys.date-time:datetime",
        "userDefined": false
      }
    ],
    "isTemplate": true,
    "count": 0,
    "updated": 1539785892
  },
  {
    "id": "f00ef69f-c0b6-4b34-944a-bc04fd5b2fea",
    "data": [
      {
        "text": "@sys.any:any @city:city @activity:activity @sys.date-time:datetime @sys.any:any",
        "userDefined": false
      }
    ],
    "isTemplate": true,
    "count": 0,
    "updated": 1539785892
  },
  {
    "id": "63adb76e-bdcc-42a0-a62d-ca2547edfb4a",
    "data": [
      {
        "text": "@city:city @sys.any:any @activity:activity @sys.date-time:datetime @sys.any:any",
        "userDefined": false
      }
    ],
    "isTemplate": true,
    "count": 0,
    "updated": 1539785892
  },
  {
    "id": "5934bdbe-041a-469b-9269-ce1fa88a7505",
    "data": [
      {
        "text": "@city:city @activity:activity @sys.any:any @sys.date-time:datetime @sys.any:any",
        "userDefined": false
      }
    ],
    "isTemplate": true,
    "count": 0,
    "updated": 1539785892
  },
  {
    "id": "2310d9a2-d11a-431e-96a9-fb29ad8f7824",
    "data": [
      {
        "text": "@sys.any:any @city:city @sys.any:any @activity:activity @sys.any:any @sys.date-time:datetime",
        "userDefined": false
      }
    ],
    "isTemplate": true,
    "count": 0,
    "updated": 1539785892
  },
  {
    "id": "83cd5bcd-b4ac-4981-b36b-414cdeb42baf",
    "data": [
      {
        "text": "@sys.any:any @city:city @sys.any:any @activity:activity @sys.date-time:datetime @sys.any:any",
        "userDefined": false
      }
    ],
    "isTemplate": true,
    "count": 0,
    "updated": 1539785892
  },
  {
    "id": "3c6a9563-064e-4e24-89ad-8af24b470e4d",
    "data": [
      {
        "text": "@sys.any:any @city:city @activity:activity @sys.any:any @sys.date-time:datetime @sys.any:any",
        "userDefined": false
      }
    ],
    "isTemplate": true,
    "count": 0,
    "updated": 1539785892
  },
  {
    "id": "73c3ddc8-262f-4698-8953-390b2dc3b40f",
    "data": [
      {
        "text": "@city:city @sys.any:any @activity:activity @sys.any:any @sys.date-time:datetime @sys.any:any",
        "userDefined": false
      }
    ],
    "isTemplate": true,
    "count": 0,
    "updated": 1539785892
  },
  {
    "id": "731594c0-8684-4851-b69e-6a21ae783c8e",
    "data": [
      {
        "text": "@sys.any:any @city:city @sys.any:any @activity:activity @sys.any:any @sys.date-time:datetime @sys.any:any",
        "userDefined": false
      }
    ],
    "isTemplate": true,
    "count": 0,
    "updated": 1539785892
  },
  {
    "id": "d49b5dca-e755-4aaf-b19b-75bc34c15e67",
    "data": [
      {
        "text": "@sys.date-time:datetime @city:city @activity:activity",
        "userDefined": false
      }
    ],
    "isTemplate": true,
    "count": 0,
    "updated": 1539785892
  },
  {
    "id": "ff0c075a-6586-435d-a370-c737e1475d60",
    "data": [
      {
        "text": "@sys.any:any @sys.date-time:datetime @city:city @activity:activity",
        "userDefined": false
      }
    ],
    "isTemplate": true,
    "count": 0,
    "updated": 1539785892
  },
  {
    "id": "3449d014-0552-4012-bee6-4c782f770d15",
    "data": [
      {
        "text": "@sys.date-time:datetime @sys.any:any @city:city @activity:activity",
        "userDefined": false
      }
    ],
    "isTemplate": true,
    "count": 0,
    "updated": 1539785892
  },
  {
    "id": "b3a67c7b-02a0-42f7-88d5-7543398e9269",
    "data": [
      {
        "text": "@sys.date-time:datetime @city:city @sys.any:any @activity:activity",
        "userDefined": false
      }
    ],
    "isTemplate": true,
    "count": 0,
    "updated": 1539785892
  },
  {
    "id": "c316147a-e199-4f6a-b638-768c93d218f9",
    "data": [
      {
        "text": "@sys.date-time:datetime @city:city @activity:activity @sys.any:any",
        "userDefined": false
      }
    ],
    "isTemplate": true,
    "count": 0,
    "updated": 1539785892
  },
  {
    "id": "f6e8a2ff-1f02-4933-85dd-438ff8b1ae57",
    "data": [
      {
        "text": "@sys.any:any @sys.date-time:datetime @sys.any:any @city:city @activity:activity",
        "userDefined": false
      }
    ],
    "isTemplate": true,
    "count": 0,
    "updated": 1539785892
  },
  {
    "id": "cfb19ef0-da04-407e-b941-ce3e038b5a8d",
    "data": [
      {
        "text": "@sys.any:any @sys.date-time:datetime @city:city @sys.any:any @activity:activity",
        "userDefined": false
      }
    ],
    "isTemplate": true,
    "count": 0,
    "updated": 1539785892
  },
  {
    "id": "43cc9d8c-ac12-4389-a281-b2e47e61ece8",
    "data": [
      {
        "text": "@sys.any:any @sys.date-time:datetime @city:city @activity:activity @sys.any:any",
        "userDefined": false
      }
    ],
    "isTemplate": true,
    "count": 0,
    "updated": 1539785892
  },
  {
    "id": "85190d56-b0eb-4e85-b6a8-76aabf01c1ae",
    "data": [
      {
        "text": "@sys.date-time:datetime @sys.any:any @city:city @activity:activity @sys.any:any",
        "userDefined": false
      }
    ],
    "isTemplate": true,
    "count": 0,
    "updated": 1539785892
  },
  {
    "id": "8ca0d4da-7fc0-4eb3-b111-339b005d3ad7",
    "data": [
      {
        "text": "@sys.date-time:datetime @city:city @sys.any:any @activity:activity @sys.any:any",
        "userDefined": false
      }
    ],
    "isTemplate": true,
    "count": 0,
    "updated": 1539785892
  },
  {
    "id": "5e2b2d34-a58c-4164-95b6-a2380fe25444",
    "data": [
      {
        "text": "@sys.any:any @sys.date-time:datetime @sys.any:any @city:city @sys.any:any @activity:activity",
        "userDefined": false
      }
    ],
    "isTemplate": true,
    "count": 0,
    "updated": 1539785892
  },
  {
    "id": "f8bc8045-3620-4166-a8b2-f38438052051",
    "data": [
      {
        "text": "@sys.any:any @sys.date-time:datetime @sys.any:any @city:city @activity:activity @sys.any:any",
        "userDefined": false
      }
    ],
    "isTemplate": true,
    "count": 0,
    "updated": 1539785892
  },
  {
    "id": "bd0d829b-dab4-41dc-8338-f8b15860ac3e",
    "data": [
      {
        "text": "@sys.any:any @sys.date-time:datetime @city:city @sys.any:any @activity:activity @sys.any:any",
        "userDefined": false
      }
    ],
    "isTemplate": true,
    "count": 0,
    "updated": 1539785892
  },
  {
    "id": "339c84b1-7154-4d4e-bbaa-66779eba2e3a",
    "data": [
      {
        "text": "@sys.date-time:datetime @sys.any:any @city:city @sys.any:any @activity:activity @sys.any:any",
        "userDefined": false
      }
    ],
    "isTemplate": true,
    "count": 0,
    "updated": 1539785892
  },
  {
    "id": "e7d0db40-a0a8-4bdb-a201-f823f9ade054",
    "data": [
      {
        "text": "@sys.any:any @sys.date-time:datetime @sys.any:any @city:city @sys.any:any @activity:activity @sys.any:any",
        "userDefined": false
      }
    ],
    "isTemplate": true,
    "count": 0,
    "updated": 1539785892
  },
  {
    "id": "bb49c5d5-726c-49ac-8bd8-e0e0047d83d3",
    "data": [
      {
        "text": "@sys.date-time:datetime @activity:activity @city:city",
        "userDefined": false
      }
    ],
    "isTemplate": true,
    "count": 0,
    "updated": 1539785892
  },
  {
    "id": "e74a3e46-e724-4e57-b0ea-97ff8a1c9b88",
    "data": [
      {
        "text": "@sys.any:any @sys.date-time:datetime @activity:activity @city:city",
        "userDefined": false
      }
    ],
    "isTemplate": true,
    "count": 0,
    "updated": 1539785892
  },
  {
    "id": "01cdb718-da61-469d-98e5-721320d3e6a9",
    "data": [
      {
        "text": "@sys.date-time:datetime @sys.any:any @activity:activity @city:city",
        "userDefined": false
      }
    ],
    "isTemplate": true,
    "count": 0,
    "updated": 1539785892
  },
  {
    "id": "b39a105a-e4a8-448e-92c1-456dcc739a94",
    "data": [
      {
        "text": "@sys.date-time:datetime @activity:activity @sys.any:any @city:city",
        "userDefined": false
      }
    ],
    "isTemplate": true,
    "count": 0,
    "updated": 1539785892
  },
  {
    "id": "89f85b99-3f25-4d68-8c68-ebad6ab00a16",
    "data": [
      {
        "text": "@sys.date-time:datetime @activity:activity @city:city @sys.any:any",
        "userDefined": false
      }
    ],
    "isTemplate": true,
    "count": 0,
    "updated": 1539785892
  },
  {
    "id": "8a4b0812-3ab9-4702-8ef4-9980f5502726",
    "data": [
      {
        "text": "@sys.any:any @sys.date-time:datetime @sys.any:any @activity:activity @city:city",
        "userDefined": false
      }
    ],
    "isTemplate": true,
    "count": 0,
    "updated": 1539785892
  },
  {
    "id": "eb1881ad-adb7-41a7-9324-f1efa16a8da4",
    "data": [
      {
        "text": "@sys.any:any @sys.date-time:datetime @activity:activity @sys.any:any @city:city",
        "userDefined": false
      }
    ],
    "isTemplate": true,
    "count": 0,
    "updated": 1539785892
  },
  {
    "id": "401069da-0d5c-499b-97b5-531a8ae511a9",
    "data": [
      {
        "text": "@sys.any:any @sys.date-time:datetime @activity:activity @city:city @sys.any:any",
        "userDefined": false
      }
    ],
    "isTemplate": true,
    "count": 0,
    "updated": 1539785892
  },
  {
    "id": "2e426b74-8353-450a-94d8-d0d7f71b7758",
    "data": [
      {
        "text": "@sys.date-time:datetime @sys.any:any @activity:activity @city:city @sys.any:any",
        "userDefined": false
      }
    ],
    "isTemplate": true,
    "count": 0,
    "updated": 1539785892
  },
  {
    "id": "de7698ae-20dd-401a-94d7-5251af59f32a",
    "data": [
      {
        "text": "@sys.date-time:datetime @activity:activity @sys.any:any @city:city @sys.any:any",
        "userDefined": false
      }
    ],
    "isTemplate": true,
    "count": 0,
    "updated": 1539785892
  },
  {
    "id": "9c64dd4c-723d-467e-8bc2-c1ec944991bf",
    "data": [
      {
        "text": "@sys.any:any @sys.date-time:datetime @sys.any:any @activity:activity @sys.any:any @city:city",
        "userDefined": false
      }
    ],
    "isTemplate": true,
    "count": 0,
    "updated": 1539785892
  },
  {
    "id": "f68f8e60-c575-4147-b77b-5ec3c05b2ee8",
    "data": [
      {
        "text": "@sys.any:any @sys.date-time:datetime @sys.any:any @activity:activity @city:city @sys.any:any",
        "userDefined": false
      }
    ],
    "isTemplate": true,
    "count": 0,
    "updated": 1539785892
  },
  {
    "id": "246aaff8-cb03-4c74-80d5-eed95c0fdcc4",
    "data": [
      {
        "text": "@sys.any:any @sys.date-time:datetime @activity:activity @sys.any:any @city:city @sys.any:any",
        "userDefined": false
      }
    ],
    "isTemplate": true,
    "count": 0,
    "updated": 1539785892
  },
  {
    "id": "eb44594f-8ac7-4bc5-9138-084181d3682e",
    "data": [
      {
        "text": "@sys.date-time:datetime @sys.any:any @activity:activity @sys.any:any @city:city @sys.any:any",
        "userDefined": false
      }
    ],
    "isTemplate": true,
    "count": 0,
    "updated": 1539785892
  },
  {
    "id": "b7e3770a-17a8-45b3-8460-53f65dbbd467",
    "data": [
      {
        "text": "@sys.any:any @sys.date-time:datetime @sys.any:any @activity:activity @sys.any:any @city:city @sys.any:any",
        "userDefined": false
      }
    ],
    "isTemplate": true,
    "count": 0,
    "updated": 1539785892
  },
  {
    "id": "514a8e75-ee99-458b-b1c6-152018e23f9b",
    "data": [
      {
        "text": "@activity:activity @city:city @sys.date-time:datetime",
        "userDefined": false
      }
    ],
    "isTemplate": true,
    "count": 0,
    "updated": 1539785892
  },
  {
    "id": "2df1c901-8377-4d14-b799-52c51b3565a9",
    "data": [
      {
        "text": "@sys.any:any @activity:activity @city:city @sys.date-time:datetime",
        "userDefined": false
      }
    ],
    "isTemplate": true,
    "count": 0,
    "updated": 1539785892
  },
  {
    "id": "9b00decf-109d-40c3-bfdb-cb5b7f90f730",
    "data": [
      {
        "text": "@activity:activity @sys.any:any @city:city @sys.date-time:datetime",
        "userDefined": false
      }
    ],
    "isTemplate": true,
    "count": 0,
    "updated": 1539785892
  },
  {
    "id": "fbdf8859-4c47-43aa-ac5a-b639602f54a4",
    "data": [
      {
        "text": "@activity:activity @city:city @sys.any:any @sys.date-time:datetime",
        "userDefined": false
      }
    ],
    "isTemplate": true,
    "count": 0,
    "updated": 1539785892
  },
  {
    "id": "3b31395d-dcab-4e5c-9944-3df96a30db9c",
    "data": [
      {
        "text": "@activity:activity @city:city @sys.date-time:datetime @sys.any:any",
        "userDefined": false
      }
    ],
    "isTemplate": true,
    "count": 0,
    "updated": 1539785892
  },
  {
    "id": "5ab3bc44-8302-487e-8c02-d09c5df41286",
    "data": [
      {
        "text": "@sys.any:any @activity:activity @sys.any:any @city:city @sys.date-time:datetime",
        "userDefined": false
      }
    ],
    "isTemplate": true,
    "count": 0,
    "updated": 1539785892
  },
  {
    "id": "6e42fd53-2ab3-4d6c-ae76-d40d67d2ec4a",
    "data": [
      {
        "text": "@sys.any:any @activity:activity @city:city @sys.any:any @sys.date-time:datetime",
        "userDefined": false
      }
    ],
    "isTemplate": true,
    "count": 0,
    "updated": 1539785892
  },
  {
    "id": "c5e3cfdd-e676-488b-bdb7-176aac23ee8a",
    "data": [
      {
        "text": "@sys.any:any @activity:activity @city:city @sys.date-time:datetime @sys.any:any",
        "userDefined": false
      }
    ],
    "isTemplate": true,
    "count": 0,
    "updated": 1539785892
  },
  {
    "id": "8b4e2f55-cc37-4e8b-aa9a-e49d38323d37",
    "data": [
      {
        "text": "@activity:activity @sys.any:any @city:city @sys.date-time:datetime @sys.any:any",
        "userDefined": false
      }
    ],
    "isTemplate": true,
    "count": 0,
    "updated": 1539785892
  },
  {
    "id": "849b8294-52ed-431f-a9a8-aaa8f75767de",
    "data": [
      {
        "text": "@activity:activity @city:city @sys.any:any @sys.date-time:datetime @sys.any:any",
        "userDefined": false
      }
    ],
    "isTemplate": true,
    "count": 0,
    "updated": 1539785892
  },
  {
    "id": "b99e00df-946f-46ec-aedc-b1fddc26510c",
    "data": [
      {
        "text": "@sys.any:any @activity:activity @sys.any:any @city:city @sys.any:any @sys.date-time:datetime",
        "userDefined": false
      }
    ],
    "isTemplate": true,
    "count": 0,
    "updated": 1539785892
  },
  {
    "id": "35560be2-f1ff-4d66-a7b2-c6dd97395ce5",
    "data": [
      {
        "text": "@sys.any:any @activity:activity @sys.any:any @city:city @sys.date-time:datetime @sys.any:any",
        "userDefined": false
      }
    ],
    "isTemplate": true,
    "count": 0,
    "updated": 1539785892
  },
  {
    "id": "81047dba-fa4a-4095-a818-a027d0d17c64",
    "data": [
      {
        "text": "@sys.any:any @activity:activity @city:city @sys.any:any @sys.date-time:datetime @sys.any:any",
        "userDefined": false
      }
    ],
    "isTemplate": true,
    "count": 0,
    "updated": 1539785892
  },
  {
    "id": "25753985-92ea-4bc5-9479-b16358a2709e",
    "data": [
      {
        "text": "@activity:activity @sys.any:any @city:city @sys.any:any @sys.date-time:datetime @sys.any:any",
        "userDefined": false
      }
    ],
    "isTemplate": true,
    "count": 0,
    "updated": 1539785892
  },
  {
    "id": "59abbf16-7c69-4573-a353-6845f699984b",
    "data": [
      {
        "text": "@sys.any:any @activity:activity @sys.any:any @city:city @sys.any:any @sys.date-time:datetime @sys.any:any",
        "userDefined": false
      }
    ],
    "isTemplate": true,
    "count": 0,
    "updated": 1539785892
  },
  {
    "id": "98e3d287-609a-45b0-b253-5b79de0583f0",
    "data": [
      {
        "text": "@activity:activity @sys.date-time:datetime @city:city",
        "userDefined": false
      }
    ],
    "isTemplate": true,
    "count": 0,
    "updated": 1539785892
  },
  {
    "id": "a0d668ec-d4c7-4bf2-a493-cc9de30a80bd",
    "data": [
      {
        "text": "@sys.any:any @activity:activity @sys.date-time:datetime @city:city",
        "userDefined": false
      }
    ],
    "isTemplate": true,
    "count": 0,
    "updated": 1539785892
  },
  {
    "id": "ee2a1a9e-442a-4e18-a6e2-a7617959e0f6",
    "data": [
      {
        "text": "@activity:activity @sys.any:any @sys.date-time:datetime @city:city",
        "userDefined": false
      }
    ],
    "isTemplate": true,
    "count": 0,
    "updated": 1539785892
  },
  {
    "id": "ba98c34c-4d1f-495d-bb31-202799e07d78",
    "data": [
      {
        "text": "@activity:activity @sys.date-time:datetime @sys.any:any @city:city",
        "userDefined": false
      }
    ],
    "isTemplate": true,
    "count": 0,
    "updated": 1539785892
  },
  {
    "id": "9253eac1-9d81-40d8-80f4-6d43f410d117",
    "data": [
      {
        "text": "@activity:activity @sys.date-time:datetime @city:city @sys.any:any",
        "userDefined": false
      }
    ],
    "isTemplate": true,
    "count": 0,
    "updated": 1539785892
  },
  {
    "id": "94641efb-c4c8-4059-b659-826ba6685b7b",
    "data": [
      {
        "text": "@sys.any:any @activity:activity @sys.any:any @sys.date-time:datetime @city:city",
        "userDefined": false
      }
    ],
    "isTemplate": true,
    "count": 0,
    "updated": 1539785892
  },
  {
    "id": "c3aafc54-fe53-4bb5-a066-0e220d924d17",
    "data": [
      {
        "text": "@sys.any:any @activity:activity @sys.date-time:datetime @sys.any:any @city:city",
        "userDefined": false
      }
    ],
    "isTemplate": true,
    "count": 0,
    "updated": 1539785892
  },
  {
    "id": "c786e0c6-b65a-43a5-b126-d957fae0e06f",
    "data": [
      {
        "text": "@sys.any:any @activity:activity @sys.date-time:datetime @city:city @sys.any:any",
        "userDefined": false
      }
    ],
    "isTemplate": true,
    "count": 0,
    "updated": 1539785892
  },
  {
    "id": "378f505a-b369-423d-b896-d8063f0e8164",
    "data": [
      {
        "text": "@activity:activity @sys.any:any @sys.date-time:datetime @city:city @sys.any:any",
        "userDefined": false
      }
    ],
    "isTemplate": true,
    "count": 0,
    "updated": 1539785892
  },
  {
    "id": "b12abe0a-007b-4406-adfa-dd6c0b04585d",
    "data": [
      {
        "text": "@activity:activity @sys.date-time:datetime @sys.any:any @city:city @sys.any:any",
        "userDefined": false
      }
    ],
    "isTemplate": true,
    "count": 0,
    "updated": 1539785892
  },
  {
    "id": "40c6cdd2-f981-4a57-a8d7-948522a94bd7",
    "data": [
      {
        "text": "@sys.any:any @activity:activity @sys.any:any @sys.date-time:datetime @sys.any:any @city:city",
        "userDefined": false
      }
    ],
    "isTemplate": true,
    "count": 0,
    "updated": 1539785892
  },
  {
    "id": "d03d594e-940f-4004-a54f-0371c75970aa",
    "data": [
      {
        "text": "@sys.any:any @activity:activity @sys.any:any @sys.date-time:datetime @city:city @sys.any:any",
        "userDefined": false
      }
    ],
    "isTemplate": true,
    "count": 0,
    "updated": 1539785892
  },
  {
    "id": "56620721-6ee6-4322-9166-16c073203b93",
    "data": [
      {
        "text": "@sys.any:any @activity:activity @sys.date-time:datetime @sys.any:any @city:city @sys.any:any",
        "userDefined": false
      }
    ],
    "isTemplate": true,
    "count": 0,
    "updated": 1539785892
  },
  {
    "id": "69f2ae69-9034-4c2e-b570-8da3be405e9d",
    "data": [
      {
        "text": "@activity:activity @sys.any:any @sys.date-time:datetime @sys.any:any @city:city @sys.any:any",
        "userDefined": false
      }
    ],
    "isTemplate": true,
    "count": 0,
    "updated": 1539785892
  },
  {
    "id": "aa539bad-dfad-4d94-9fee-3860991fdad7",
    "data": [
      {
        "text": "@sys.any:any @activity:activity @sys.any:any @sys.date-time:datetime @sys.any:any @city:city @sys.any:any",
        "userDefined": false
      }
    ],
    "isTemplate": true,
    "count": 0,
    "updated": 1539785892
  }
]